AUTHORS
CHANGELOG.md
LICENSE
MANIFEST.in
README.md
setup.cfg
setup.py
versioneer.py
src/libreflow/__init__.py
src/libreflow.flows.egg-info/PKG-INFO
src/libreflow.flows.egg-info/SOURCES.txt
src/libreflow.flows.egg-info/dependency_links.txt
src/libreflow.flows.egg-info/requires.txt
src/libreflow.flows.egg-info/top_level.txt
src/libreflow/flows/__init__.py
src/libreflow/flows/_version.py
src/libreflow/flows/cli.py
src/libreflow/flows/gui.py
src/libreflow/flows/custom_home/__init__.py
src/libreflow/flows/custom_home/ui.py
src/libreflow/flows/default/__init__.py
src/libreflow/flows/default/flow/__init__.py
src/libreflow/flows/default/flow/asset.py
src/libreflow/flows/default/flow/entity_manager.py
src/libreflow/flows/default/flow/file.py
src/libreflow/flows/default/flow/film.py
src/libreflow/flows/default/flow/shot.py
src/libreflow/flows/default/flow/task.py
src/libreflow/flows/default/flow/user.py
src/libreflow/flows/resources/__init__.py
src/libreflow/flows/resources/file_templates/__init__.py
src/libreflow/flows/resources/file_templates/template.blend
src/libreflow/flows/resources/file_templates/template.wav
src/libreflow/flows/resources/gifs/__init__.py
src/libreflow/flows/resources/gifs/magic_word.gif
src/libreflow/flows/resources/gui/__init__.py
src/libreflow/flows/resources/gui/styles/__init__.py
src/libreflow/flows/resources/gui/styles/default_style/__init__.py
src/libreflow/flows/resources/gui/styles/default_style/default_style.css
src/libreflow/flows/tinykin/__init__.py
src/libreflow/flows/tinykin/flow/__init__.py
src/libreflow/flows/tinykin/flow/file.py
src/libreflow/flows/tinykin/flow/film.py
src/libreflow/flows/tinykin/flow/lib.py
src/libreflow/flows/tinykin/flow/users.py
src/libreflow/flows/tinykin/resources/__init__.py
src/libreflow/flows/tinykin/resources/file_templates/__init__.py
src/libreflow/flows/tinykin/resources/file_templates/template.blend
src/libreflow/flows/tinykin/resources/icons/__init__.py
src/libreflow/flows/tinykin/resources/icons/flow/__init__.py
src/libreflow/flows/tinykin/resources/icons/flow/publish-ok.png