Metadata-Version: 2.4
Name: libreflow.flows
Version: 2.7.0
Summary: A set of flows specific to projects handled by Libreflow at Les Fées Spéciales.
Home-page: https://gitlab.com/lfs.coop/libreflow/libreflow.flows
Author: Baptiste Delos, Flavio Perez
Author-email: baptiste@les-fees-speciales.coop, flavio@lfs.coop
License: LGPLv3+
Keywords: kabaret cgwire kitsu gazu animation pipeline libreflow
Classifier: Programming Language :: Python :: 3
Classifier: Intended Audience :: Developers
Classifier: Intended Audience :: End Users/Desktop
Classifier: Intended Audience :: Information Technology
Classifier: License :: OSI Approved :: GNU Lesser General Public License v3 or later (LGPLv3+)
Classifier: Operating System :: OS Independent
Requires-Python: >=3.8
License-File: LICENSE
License-File: AUTHORS
Requires-Dist: libreflow>=2.10.0
Requires-Dist: kabaret.flow_extensions>=1.0.0
Dynamic: author
Dynamic: author-email
Dynamic: classifier
Dynamic: description
Dynamic: description-content-type
Dynamic: home-page
Dynamic: keywords
Dynamic: license
Dynamic: license-file
Dynamic: requires-dist
Dynamic: requires-python
Dynamic: summary
